LICENSE
MANIFEST.in
README.rst
setup.py
django_password_session.egg-info/PKG-INFO
django_password_session.egg-info/SOURCES.txt
django_password_session.egg-info/dependency_links.txt
django_password_session.egg-info/requires.txt
django_password_session.egg-info/top_level.txt
password_session/__init__.py
password_session/handlers.py
password_session/middleware.py
password_session/models.py